{
  "name": "minimalist-html-demo",
  "version": "1.0.15",
  "author": {
    "name": "Arcblock"
  },
  "repository": {
    "type": "git",
    "url": "git+ssh://git@github.com/blocklet/minimalist-html-demo.git"
  },
  "main": ".",
  "license": "MIT",
  "files": [
    "blocklet.md",
    "README.md",
    "index.html"
  ],
  "title": "Simple HTML Demo",
  "keywords": [
    "static",
    "demo",
    "html"
  ],
  "description": "A minimalist Blocklet demo with plain HTML. It's simple a web page.",
  "group": "static",
  "specVersion": "1.2.1",
  "did": "z8iZjejYpy7TeJbTq6oXLbVgXemAMbpqwM17Q",
  "community": "",
  "documentation": "",
  "homepage": "",
  "interfaces": [
    {
      "type": "web",
      "name": "publicUrl",
      "path": "/",
      "prefix": "*",
      "port": "BLOCKLET_PORT",
      "protocol": "tcp"
    }
  ],
  "environments": [],
  "screenshots": [],
  "scripts": {},
  "timeout": {
    "start": 10
  },
  "requirements": {
    "abtnode": ">=1.1.0",
    "os": "*",
    "cpu": "*"
  },
  "payment": {
    "price": [],
    "share": []
  },
  "children": [],
  "capabilities": {
    "clusterMode": false
  },
  "gitHash": "0209ad444ca910384ba80f1fcd9857846a1fa0ac",
  "path": "/static/minimalist-html-demo",
  "nftFactory": "",
  "dist": {
    "tarball": "minimalist-html-demo-1.0.15.tgz",
    "integrity": "sha512-lX0CuzeoyV+ScfOGN+lJ9W1F7aTHp5r8vwv9Z7kxOeqRahNTE9jJ75mQ3SlViQaF8xApRAUmPU10RKy/LbCVqw=="
  }
}
